---
source: https://o.alldu.cn/docs/jvm-%E6%A0%B8%E5%BF%83%E6%8A%80%E6%9C%AF-32-%E8%AE%B2%E5%AE%8C/05-java-%E5%AD%97%E8%8A%82%E7%A0%81%E6%8A%80%E6%9C%AF%E4%B8%8D%E7%A7%AF%E7%BB%86%E6%B5%81%E6%97%A0%E4%BB%A5%E6%88%90%E6%B1%9F%E6%B2%B3/#45-%e6%9f%a5%e7%9c%8b%e6%96%b9%e6%b3%95%e4%bf%a1%e6%81%af
type: input
banner: Assets/Banner/pexels-samkolder-2387877.jpg
---
# ğŸ“° é˜…è¯»ç¬”è®°

## 1	å­—èŠ‚ç ç®€è¿°

Java ByteCode ç”±å•å­—èŠ‚çš„æŒ‡ä»¤æ„æˆ, ç†è®ºæœ€å¤šæ”¯æŒ 256 ä¸ªæ“ä½œç , Java ä½¿ç”¨äº† 200 ä¸ªå·¦å³.

æŒ‡ä»¤ç”± **ç±»å‹å‰ç¼€ + æ“ä½œåç§°** æ„æˆ, æ¯”å¦‚ iadd, ä»£è¡¨ integer_add.

æ ¹æ®æŒ‡ä»¤çš„æ€§è´¨, å¯ä»¥å°†æŒ‡ä»¤åˆ†ä¸º: 

- **æ ˆæ“ä½œ**æŒ‡ä»¤, åŒ…æ‹¬ä¸å±€éƒ¨å˜é‡äº¤äº’çš„æŒ‡ä»¤
	
- **ç¨‹åºæµç¨‹æ§åˆ¶**æŒ‡ä»¤
	
- **å¯¹è±¡æ“ä½œ**æŒ‡ä»¤, åŒ…æ‹¬æ–¹æ³•è°ƒç”¨æŒ‡ä»¤
	
- **ç®—æœ¯è¿ç®—**ä»¥åŠ**ç±»å‹è½¬æ¢**æŒ‡ä»¤

## 2	å­—èŠ‚ç æ¸…å•è§£è¯»

### 2.1	è·å–å­—èŠ‚ç æ¸…å•

```java
public class JavaByteCodeDemo {  
    public static void main(String[] args) {  
        JavaByteCodeDemo javaByteCodeDemo = new JavaByteCodeDemo();  
    }  
}

// ====== ç¼–è¯‘å ======

Compiled from "JavaByteCodeDemo.java"
public class com.ryan.demo.JavaByteCodeDemo {
  public com.ryan.demo.JavaByteCodeDemo();
    Code:
       0: aload_0
       1: invokespecial #1                  // Method java/lang/Object."<init>":()V
       4: return

  public static void main(java.lang.String[]);
    Code:
       0: new           #7                  // class com/ryan/demo/JavaByteCodeDemo
       3: dup
       4: invokespecial #9                  // Method "<init>":()V
       7: astore_1
       8: return
}
```

### 2.2	è§£è¯»å­—èŠ‚ç æ¸…å•

```java
  public com.ryan.demo.JavaByteCodeDemo();
    Code:
       0: aload_0
       1: invokespecial #1                  // Method java/lang/Object."<init>":()V
       4: return
```

è‡ªåŠ¨ç”Ÿæˆçš„æ„é€ æ–¹æ³•, å†…éƒ¨çš„ä¸‰è¡Œä»£ç è¡¨ç¤ºå¯¹ super() çš„è°ƒç”¨.

```java
  public static void main(java.lang.String[]);
    Code:
       0: new           #7                  // class com/ryan/demo/JavaByteCodeDemo
       3: dup
       4: invokespecial #9                  // Method "<init>":()V
       7: astore_1
       8: return
```

åˆ›å»ºä¸€ä¸ªç±»å®ä¾‹ç„¶åè¿”å›.

### 2.3	æŸ¥çœ‹æ–‡ä»¶çš„å¸¸é‡æ± ä¿¡æ¯

é€šè¿‡ javap çš„ -v é€‰é¡¹æ¥è¾“å‡ºè¯¦ç»†ä¿¡æ¯.

```java
Classfile /D:/code/personal/demo-projects/src/main/java/com/ryan/demo/JavaByteCodeDemo.class
  Last modified 2025å¹´12æœˆ17æ—¥; size 465 bytes
  SHA-256 checksum be2ba80ca51be1a64fc9cf0b5a3e51ff27ed966ffb9625901e315b582461a990
  Compiled from "JavaByteCodeDemo.java"
public class com.ryan.demo.JavaByteCodeDemo
  minor version: 0
  major version: 61
  flags: (0x0021) ACC_PUBLIC, ACC_SUPER
  this_class: #7                          // com/ryan/demo/JavaByteCodeDemo
  super_class: #2                         // java/lang/Object
  interfaces: 0, fields: 0, methods: 2, attributes: 1
Constant pool:
   #1 = Methodref          #2.#3          // java/lang/Object."<init>":()V
   #2 = Class              #4             // java/lang/Object
   #3 = NameAndType        #5:#6          // "<init>":()V
   #4 = Utf8               java/lang/Object
   #5 = Utf8               <init>
   #6 = Utf8               ()V
   #7 = Class              #8             // com/ryan/demo/JavaByteCodeDemo
   #8 = Utf8               com/ryan/demo/JavaByteCodeDemo
   #9 = Methodref          #7.#3          // com/ryan/demo/JavaByteCodeDemo."<init>":()V
  #10 = Utf8               Code
  #11 = Utf8               LineNumberTable
  #12 = Utf8               LocalVariableTable
  #13 = Utf8               this
  #14 = Utf8               Lcom/ryan/demo/JavaByteCodeDemo;
  #15 = Utf8               main
  #16 = Utf8               ([Ljava/lang/String;)V
  #17 = Utf8               args
  #18 = Utf8               [Ljava/lang/String;
  #19 = Utf8               javaByteCodeDemo
  #20 = Utf8               SourceFile
  #21 = Utf8               JavaByteCodeDemo.java
{
  public com.ryan.demo.JavaByteCodeDemo();
    descriptor: ()V
    flags: (0x0001) ACC_PUBLIC
    Code:
      stack=1, locals=1, args_size=1
         0: aload_0
         1: invokespecial #1                  // Method java/lang/Object."<init>":()V
         4: return
      LineNumberTable:
        line 9: 0
      LocalVariableTable:
        Start  Length  Slot  Name   Signature
            0       5     0  this   Lcom/ryan/demo/JavaByteCodeDemo;

  public static void main(java.lang.String[]);
    descriptor: ([Ljava/lang/String;)V
    flags: (0x0009) ACC_PUBLIC, ACC_STATIC
    Code:
      stack=2, locals=2, args_size=1
         0: new           #7                  // class com/ryan/demo/JavaByteCodeDemo
         3: dup
         4: invokespecial #9                  // Method "<init>":()V
         7: astore_1
         8: return
      LineNumberTable:
        line 12: 0
        line 13: 8
      LocalVariableTable:
        Start  Length  Slot  Name   Signature
            0       9     0  args   [Ljava/lang/String;
            8       1     1 javaByteCodeDemo   Lcom/ryan/demo/JavaByteCodeDemo;
}
SourceFile: "JavaByteCodeDemo.java"
```

å…¶ä¸­æ˜¾ç¤ºäº†å¾ˆå¤šå…³äº class æ–‡ä»¶ä¿¡æ¯: ç¼–è¯‘æ—¶é—´, MD5 æ ¡éªŒå’Œ, ä»å“ªä¸ª . java æºæ–‡ä»¶ç¼–è¯‘å¾—æ¥, ç¬¦åˆå“ªä¸ªç‰ˆæœ¬çš„ Java è¯­è¨€è§„èŒƒç­‰ç­‰. è¿˜å¯ä»¥çœ‹åˆ° ACC_PUBLIC å’Œ ACC_SUPER è®¿é—®æ ‡å¿—ç¬¦. ACC_PUBLIC æ ‡å¿—å¾ˆå®¹æ˜“ç†è§£:è¿™ä¸ªç±»æ˜¯ public ç±», å› æ­¤ç”¨è¿™ä¸ªæ ‡å¿—æ¥è¡¨ç¤º.

å…¶ä¸­ # æ˜¯å¯¹å¸¸é‡æ± çš„å¼•ç”¨.

### 2.4	æŸ¥çœ‹æ–¹æ³•ä¿¡æ¯

```java
public static void main(java.lang.String[]);
    descriptor: ([Ljava/lang/String;)V
    flags: (0x0009) ACC_PUBLIC, ACC_STATIC
    Code:
      stack=2, locals=2, args_size=1
```

- descriptor éƒ¨åˆ†çš„å°æ‹¬å·å†…æ˜¯å…¥å‚ä¿¡æ¯/å½¢å‚ä¿¡æ¯, å·¦æ–¹æ‹¬å·è¡¨è¿°æ•°ç»„; L è¡¨ç¤ºå¯¹è±¡; åé¢çš„ java/lang/String å°±æ˜¯ç±»åç§°, å°æ‹¬å·åé¢çš„ V åˆ™è¡¨ç¤ºè¿™ä¸ªæ–¹æ³•çš„è¿”å›å€¼æ˜¯ void;
	
- ACC_PUBLIC, ACC_STATIC, è¡¨ç¤º public å’Œ static.
	
- è¿˜å¯ä»¥çœ‹åˆ°æ‰§è¡Œè¯¥æ–¹æ³•æ—¶éœ€è¦çš„ stack æ·±åº¦æ˜¯ 2, ä¹Ÿå°±æ˜¯åŒæ—¶åœ¨æ ˆä¸Šæœ€å¤šä¼šæœ‰ä¸¤ä¸ªå€¼
	
- éœ€è¦åœ¨å±€éƒ¨å˜é‡è¡¨ä¸­ä¿ç•™ 2 ä¸ªæ§½ä½, è¿˜æœ‰æ–¹æ³•çš„å‚æ•°ä¸ªæ•°ä¸º 1:

### 2.5	æ–¹æ³•ä½“ä¸­çš„å­—èŠ‚ç è§£è¯»

```java
 0: new           #7                  // class com/ryan/demo/JavaByteCodeDemo
 3: dup
 4: invokespecial #9                  // Method "<init>":()V
 7: astore_1
 8: return
```

åºå·è¡¨ç¤ºè¿™ä¸ªå‘½ä»¤èµ·ç‚¹ä½äºå“ªä¸ªå­—èŠ‚ç æ§½ä½, ä¾‹å¦‚, new å ç”¨ä¸‰ä¸ªæ“ä½œ, å› ä¸ºé™¤äº†æ“ä½œç , è¿˜å­˜æœ‰æ“ä½œæ•°.

![[Java å­—èŠ‚ç æ§½ä½ç¤ºæ„å›¾.png|800]]





---

# ğŸ’­ æˆ‘çš„æ€è€ƒ

è¿™ä¸ªè§‚ç‚¹å¦‚ä½•ä¸æˆ‘å·²çŸ¥çš„çŸ¥è¯†äº§ç”Ÿè”ç³»? å®ƒè®©æˆ‘æƒ³åˆ°äº†ä»€ä¹ˆ?